lightwin/constants.py
lightwin/__init__.py
lightwin/visualization/specs.py
lightwin/visualization/plot.py
lightwin/visualization/anim.py
lightwin/visualization/data_getter.py
lightwin/visualization/optimization.py
lightwin/visualization/__init__.py
lightwin/visualization/helper.py
lightwin/visualization/structure.py
lightwin/visualization/ellipse.py
lightwin/failures/set_of_cavity_settings.py
lightwin/failures/__init__.py
lightwin/failures/strategy.py
lightwin/failures/helper.py
lightwin/failures/fault.py
lightwin/failures/fault_scenario.py
lightwin/ui/__init__.py
lightwin/ui/workflow_setup.py
lightwin/evaluator/specs.py
lightwin/evaluator/post_treaters.py
lightwin/evaluator/__init__.py
lightwin/evaluator/types.py
lightwin/evaluator/list_of_simulation_output_evaluators.py
lightwin/evaluator/testers.py
lightwin/evaluator/helper.py
lightwin/evaluator/simulation_output/presets.py
lightwin/evaluator/simulation_output/__init__.py
lightwin/evaluator/simulation_output/factory.py
lightwin/evaluator/simulation_output/simulation_output_evaluator.py
lightwin/experimental/__init__.py
lightwin/experimental/test.py
lightwin/experimental/new_evaluator/__init__.py
lightwin/experimental/new_evaluator/i_evaluator.py
lightwin/experimental/new_evaluator/simulation_output/i_simulation_output_evaluator.py
lightwin/experimental/new_evaluator/simulation_output/presets.py
lightwin/experimental/new_evaluator/simulation_output/__init__.py
lightwin/experimental/new_evaluator/simulation_output/factory.py
lightwin/experimental/plotter/matplotlib_helper.py
lightwin/experimental/plotter/__init__.py
lightwin/experimental/plotter/i_plotter.py
lightwin/experimental/plotter/matplotlib_plotter.py
lightwin/core/instructions_factory.py
lightwin/core/__init__.py
lightwin/core/files_specs.py
lightwin/core/beam_specs.py
lightwin/core/particle.py
lightwin/core/instruction.py
lightwin/core/beam_parameters/initial_beam_parameters.py
lightwin-0.15.0.dist-info/RECORD
lightwin-0.15.0.dist-info/WHEEL
lightwin-0.15.0.dist-info/entry_points.txt
lightwin-0.15.0.dist-info/top_level.txt
lightwin-0.15.0.dist-info/METADATA
lightwin-0.15.0.dist-info/licenses/LICENSE
lightwin-0.15.0.dist-info/licenses/CITATION.cff
