Metadata-Version: 2.4
Name: LightWin
Version: 0.15.0
Summary: Automatically compensate cavity failures in linacs
Author-email: Adrien Plaçais <placais@lpsc.in2p3.fr>, Bruce Yee-Rendon <byee@post.j-parc.jp>, Didier Uriot <didier.uriot@cea.fr>, Frédéric Bouly <bouly@lpsc.in2p3.fr>, Jean-Michel Lagniel <jean-michel.lagniel@ganil.fr>
License-Expression: MIT
Project-URL: changelog, https://github.com/AdrienPlacais/LightWin/blob/main/CHANGELOG.md
Project-URL: discussions, https://github.com/AdrienPlacais/LightWin/discussions
Project-URL: documentation, https://lightwin.readthedocs.io/en/latest/
Project-URL: homepage, https://github.com/AdrienPlacais/LightWin
Project-URL: tracker, https://github.com/AdrienPlacais/LightWin/issues
Keywords: failure compensation,linac,linear accelerator,reliability
Classifier: Development Status :: 3 - Alpha
Classifier: Intended Audience :: Science/Research
Classifier: Operating System :: OS Independent
Classifier: Programming Language :: Python :: 3.12
Classifier: Topic :: Scientific/Engineering :: Physics
Requires-Python: >=3.12
License-File: LICENSE
License-File: CITATION.cff
Requires-Dist: bayesian-optimization<4,>=3.1
Requires-Dist: cloudpickle<4,>=3
Requires-Dist: matplotlib<4,>=3.9.1
Requires-Dist: numpy<3,>=2
Requires-Dist: pandas<3,>=2.2
Requires-Dist: pandas-stubs<3,>=2.3
Requires-Dist: palettable<4,>=3.3.3
Requires-Dist: pre-commit<5,>=4
Requires-Dist: scipy<2,>=1.14
Provides-Extra: cython
Requires-Dist: cython<4,>=3.2; extra == "cython"
Provides-Extra: docs
Requires-Dist: myst-parser<5,>=4; extra == "docs"
Requires-Dist: nbsphinx<1,>=0.9.6; extra == "docs"
Requires-Dist: sphinx-autodoc-typehints<4,>=3.0.1; extra == "docs"
Requires-Dist: sphinx-rtd-theme<4,>=3; extra == "docs"
Requires-Dist: sphinx-tabs<4,>=3.4; extra == "docs"
Requires-Dist: sphinxcontrib-bibtex<3,>=2.6; extra == "docs"
Provides-Extra: test
Requires-Dist: pytest<9,>=8.3.2; extra == "test"
Dynamic: license-file
